setup.py
pyearthquake/__init__.py
pyearthquake/httputil.py
pyearthquake/modis.py
pyearthquake/usgs.py
pyearthquake.egg-info/PKG-INFO
pyearthquake.egg-info/SOURCES.txt
pyearthquake.egg-info/dependency_links.txt
pyearthquake.egg-info/requires.txt
pyearthquake.egg-info/top_level.txt