Metadata-Version: 1.0
Name: pyearthquake
Version: 0.5
Summary: Python Earthquake and MODIS utilities
Home-page: http://pyevolve.sourceforge.net/wordpress
Author: Christian S. Perone
Author-email: christian.perone@gmail.com
License: GPLv2
Keywords: python modis usgs earthquake analysis aqua terra satellite
Platform: UNKNOWN
